pymola/__init__.py
pymola/gen_sympy.py
pymola/gen_sympy2.py
pymola/version.py
pymola/generated/ModelicaLexer.py
pymola/generated/ModelicaListener.py
pymola/generated/ModelicaParser.py
pymola/generated/__init__.py
pymola/templates/__init__.py
pymola/test/__init__.py
pymola/test/test.py
pymola-0.0.5.dist-info/DESCRIPTION.rst
pymola-0.0.5.dist-info/METADATA
pymola-0.0.5.dist-info/RECORD
pymola-0.0.5.dist-info/WHEEL
pymola-0.0.5.dist-info/metadata.json
pymola-0.0.5.dist-info/top_level.txt
